{
  "name": "Search and Rescue",
  "overview": "A search is an emergency situation requiring a team of trained searchers to locate a missing person. A rescue is an emergency situation where a person’s location is known – perhaps having just been found by searchers – and he or she must be removed from danger and returned to safety. By working on the Search and Rescue merit badge, you will learn and practice many skills that may someday save a life.",
  "is_eagle_required": false,
  "is_lab": false,
  "url": "https://www.scouting.org/merit-badges/search-and-rescue/",
  "pdf_url": "https://filestore.scouting.org/filestore/Merit_Badge_ReqandRes/Pamphlets/Search%20and%20Rescue.pdf",
  "workbook_pdf_url": "http://usscouts.org/mb/worksheets/Search-and-Rescue.pdf",
  "workbook_docx_url": "http://usscouts.org/mb/worksheets/Search-and-Rescue.docx",
  "shop_url": "https://www.scoutshop.org/search-rescue-merit-badge-pamphlet-660209.html",
  "image_url": "https://www.scouting.org/wp-content/uploads/elementor/thumbs/SearchRescue-qjjk7nbqjdp20a8bkyxk52eqcw9x9weiflmucyyp28.png",
  "image_filename": "search-and-rescue-merit-badge.jpg",
  "requirements": [
    {
      "id": "15674",
      "label": null,
      "content": [
        {
          "type": "element",
          "tag": "b",
          "attrs": {},
          "children": [
            {
              "type": "text",
              "value": "A Note About Prohibited Activities "
            },
            {
              "type": "text",
              "value": " "
            },
            {
              "type": "text",
              "value": " "
            },
            {
              "type": "text",
              "value": " The Scouting America's "
            },
            {
              "type": "element",
              "tag": "em",
              "attrs": {},
              "children": [
                {
                  "type": "text",
                  "value": "Guide to Safe Scouting"
                }
              ]
            },
            {
              "type": "text",
              "value": " states under \"Prohibited Activities\" that flying in aircraft as part of a search and rescue mission is a prohibited activity for youth members. For complete information, see Scouting America's "
            },
            {
              "type": "element",
              "tag": "a",
              "attrs": {
                "href": "https://www.scouting.org/health-and-safety/gss/"
              },
              "children": [
                {
                  "type": "element",
                  "tag": "i",
                  "attrs": {},
                  "children": [
                    {
                      "type": "text",
                      "value": "Guide to Safe Scouting."
                    }
                  ]
                }
              ]
            }
          ]
        }
      ],
      "resources": [],
      "sub_requirements": []
    },
    {
      "id": "15676",
      "label": "1",
      "content": [
        {
          "type": "element",
          "tag": "b",
          "attrs": {},
          "children": [
            {
              "type": "text",
              "value": "Hazards and First Aid."
            }
          ]
        },
        {
          "type": "text",
          "value": " Do the following:"
        }
      ],
      "resources": [],
      "sub_requirements": [
        {
          "id": "15677",
          "label": "a",
          "content": [
            {
              "type": "text",
              "value": "Show or explain first aid for, and prevention of, injuries and conditions that searchers and subjects could develop during an SAR situation, including:"
            }
          ],
          "resources": [],
          "sub_requirements": []
        },
        {
          "id": "15715",
          "label": "1",
          "content": [
            {
              "type": "text",
              "value": "Dehydration"
            }
          ],
          "resources": [],
          "sub_requirements": []
        },
        {
          "id": "15716",
          "label": "2",
          "content": [
            {
              "type": "text",
              "value": "Heatstroke"
            }
          ],
          "resources": [],
          "sub_requirements": []
        },
        {
          "id": "15717",
          "label": "3",
          "content": [
            {
              "type": "text",
              "value": "Hypothermia"
            }
          ],
          "resources": [],
          "sub_requirements": []
        },
        {
          "id": "15718",
          "label": "4",
          "content": [
            {
              "type": "text",
              "value": "Shock"
            }
          ],
          "resources": [],
          "sub_requirements": []
        },
        {
          "id": "15719",
          "label": "5",
          "content": [
            {
              "type": "text",
              "value": "Blisters"
            }
          ],
          "resources": [],
          "sub_requirements": []
        },
        {
          "id": "15720",
          "label": "6",
          "content": [
            {
              "type": "text",
              "value": "Eye injuries"
            }
          ],
          "resources": [],
          "sub_requirements": []
        },
        {
          "id": "15721",
          "label": "7",
          "content": [
            {
              "type": "text",
              "value": "Ankle and knee sprains"
            }
          ],
          "resources": [],
          "sub_requirements": []
        },
        {
          "id": "15722",
          "label": "8",
          "content": [
            {
              "type": "text",
              "value": "Bug bites of chiggers, ticks, mosquitoes, and biting gnats"
            }
          ],
          "resources": [],
          "sub_requirements": []
        },
        {
          "id": "15723",
          "label": "9",
          "content": [
            {
              "type": "text",
              "value": "Bee stings"
            }
          ],
          "resources": [],
          "sub_requirements": []
        },
        {
          "id": "15724",
          "label": "10",
          "content": [
            {
              "type": "text",
              "value": "Bites of spiders"
            }
          ],
          "resources": [],
          "sub_requirements": []
        },
        {
          "id": "15725",
          "label": "11",
          "content": [
            {
              "type": "text",
              "value": "Sting of a scorpion"
            }
          ],
          "resources": [],
          "sub_requirements": []
        },
        {
          "id": "15726",
          "label": "12",
          "content": [
            {
              "type": "text",
              "value": "Bite of a wild mammal"
            }
          ],
          "resources": [],
          "sub_requirements": []
        },
        {
          "id": "15727",
          "label": "13",
          "content": [
            {
              "type": "text",
              "value": "Bite of a venomous snake."
            }
          ],
          "resources": [],
          "sub_requirements": []
        },
        {
          "id": "15678",
          "label": "b",
          "content": [
            {
              "type": "text",
              "value": "Explain how the Scout Essentials address hazards outdoors and help lost Scouts stay safe before they are rescued."
            }
          ],
          "resources": [],
          "sub_requirements": []
        },
        {
          "id": "15728",
          "label": "c",
          "content": [
            {
              "type": "text",
              "value": "Discuss how the safety gear carried by SAR team members in their field packs address SAR hazards."
            }
          ],
          "resources": [],
          "sub_requirements": []
        }
      ]
    },
    {
      "id": "15679",
      "label": "2",
      "content": [
        {
          "type": "element",
          "tag": "b",
          "attrs": {},
          "children": [
            {
              "type": "text",
              "value": "Staying and Getting Found."
            }
          ]
        },
        {
          "type": "text",
          "value": " Do the following:"
        }
      ],
      "resources": [],
      "sub_requirements": [
        {
          "id": "15680",
          "label": "a",
          "content": [
            {
              "type": "text",
              "value": "Explain how a trip plan and the buddy system help Scouts with staying found and getting found."
            }
          ],
          "resources": [],
          "sub_requirements": []
        },
        {
          "id": "15681",
          "label": "b",
          "content": [
            {
              "type": "text",
              "value": "Explain how seasonal and daily weather changes affect Trip Plans."
            }
          ],
          "resources": [],
          "sub_requirements": []
        },
        {
          "id": "15682",
          "label": "c",
          "content": [
            {
              "type": "text",
              "value": "Explain and show how a lost Scout could send signals that would alert a ground, airborne, or water SAR team to their location."
            }
          ],
          "resources": [],
          "sub_requirements": []
        },
        {
          "id": "15729",
          "label": "d",
          "content": [
            {
              "type": "text",
              "value": "Demonstrate how to use a signaling mirror."
            }
          ],
          "resources": [],
          "sub_requirements": []
        },
        {
          "id": "15730",
          "label": "e",
          "content": [
            {
              "type": "text",
              "value": "Explain how a Personal Locator Beacon (PLB) works and the role of the Air Force Rescue Coordination Center (AFRCC)."
            }
          ],
          "resources": [],
          "sub_requirements": []
        }
      ]
    },
    {
      "id": "15683",
      "label": "3",
      "content": [
        {
          "type": "element",
          "tag": "b",
          "attrs": {},
          "children": [
            {
              "type": "text",
              "value": "Maps."
            }
          ]
        },
        {
          "type": "text",
          "value": " Using a map, a compass and a GPS device or app approved by your counselor, do the following:"
        }
      ],
      "resources": [],
      "sub_requirements": [
        {
          "id": "15693",
          "label": "a",
          "content": [
            {
              "type": "text",
              "value": "Point out and explain the 5 D's (Date, Description, Details, Direction or Declination, Distance) of the map."
            }
          ],
          "resources": [],
          "sub_requirements": []
        },
        {
          "id": "15694",
          "label": "b",
          "content": [
            {
              "type": "text",
              "value": "Choose a location on the map and record the altitude, latitude, longitude, and US National Grid coordinates. Describe how these coordinate systems differ."
            }
          ],
          "resources": [],
          "sub_requirements": []
        },
        {
          "id": "15684",
          "label": "c",
          "content": [
            {
              "type": "text",
              "value": "Orient the map and take a bearing to another map location. Estimate the distance between, and describe the terrain between, the two locations."
            }
          ],
          "resources": [],
          "sub_requirements": []
        },
        {
          "id": "15731",
          "label": "d",
          "content": [
            {
              "type": "text",
              "value": "Show a hypothetical place last seen and point out an area on your map that could be used for containment using natural or human-made boundaries."
            }
          ],
          "resources": [],
          "sub_requirements": []
        }
      ]
    },
    {
      "id": "15713",
      "label": "4",
      "content": [
        {
          "type": "element",
          "tag": "b",
          "attrs": {},
          "children": [
            {
              "type": "text",
              "value": "Incident Command System (ICS)."
            }
          ]
        },
        {
          "type": "text",
          "value": " Do the following:"
        }
      ],
      "resources": [],
      "sub_requirements": [
        {
          "id": "15732",
          "label": "a",
          "content": [
            {
              "type": "text",
              "value": "Explain how a local ICS is organized and how it compares with Scouting's patrol method."
            }
          ],
          "resources": [],
          "sub_requirements": []
        },
        {
          "id": "15733",
          "label": "b",
          "content": [
            {
              "type": "text",
              "value": "Explain how local community agencies work to train for and manage search and rescue situations."
            }
          ],
          "resources": [],
          "sub_requirements": []
        }
      ]
    },
    {
      "id": "15714",
      "label": "5",
      "content": [
        {
          "type": "element",
          "tag": "b",
          "attrs": {},
          "children": [
            {
              "type": "text",
              "value": "SAR Teams."
            }
          ]
        },
        {
          "type": "text",
          "value": " Do the following:"
        }
      ],
      "resources": [],
      "sub_requirements": [
        {
          "id": "15734",
          "label": "a",
          "content": [
            {
              "type": "text",
              "value": "Explain the official duties of a search and rescue team."
            }
          ],
          "resources": [],
          "sub_requirements": []
        },
        {
          "id": "15735",
          "label": "b",
          "content": [
            {
              "type": "text",
              "value": "Explain the differences between wilderness, urban, and water SARs."
            }
          ],
          "resources": [],
          "sub_requirements": []
        },
        {
          "id": "15736",
          "label": "c",
          "content": [
            {
              "type": "text",
              "value": "Identify four types of search and rescue teams and explain situations where they are used."
            }
          ],
          "resources": [],
          "sub_requirements": []
        }
      ]
    },
    {
      "id": "15695",
      "label": "6",
      "content": [
        {
          "type": "element",
          "tag": "b",
          "attrs": {},
          "children": [
            {
              "type": "text",
              "value": "Search and Rescue Procedures."
            }
          ]
        },
        {
          "type": "text",
          "value": " Do the following:"
        }
      ],
      "resources": [],
      "sub_requirements": [
        {
          "id": "15696",
          "label": "a",
          "content": [
            {
              "type": "text",
              "value": "Explain the difference between search and rescue."
            }
          ],
          "resources": [],
          "sub_requirements": []
        },
        {
          "id": "15697",
          "label": "b",
          "content": [
            {
              "type": "text",
              "value": "Explain the difference between PLS (place last seen) and LKP (last known point)"
            }
          ],
          "resources": [],
          "sub_requirements": []
        },
        {
          "id": "15698",
          "label": "c",
          "content": [
            {
              "type": "text",
              "value": "Explain the importance of effective communication in SAR operations."
            }
          ],
          "resources": [],
          "sub_requirements": []
        },
        {
          "id": "15737",
          "label": "d",
          "content": [
            {
              "type": "text",
              "value": "Explain how predictions of \"lost person behavior\" determine SAR search plans for a young child, a teenager, and an adult."
            }
          ],
          "resources": [],
          "sub_requirements": []
        },
        {
          "id": "15738",
          "label": "e",
          "content": [
            {
              "type": "text",
              "value": "Explain the following terms:"
            }
          ],
          "resources": [],
          "sub_requirements": []
        },
        {
          "id": "15739",
          "label": "1",
          "content": [
            {
              "type": "text",
              "value": "Evaluating search urgency"
            }
          ],
          "resources": [],
          "sub_requirements": []
        },
        {
          "id": "15740",
          "label": "2",
          "content": [
            {
              "type": "text",
              "value": "Establishing confinement"
            }
          ],
          "resources": [],
          "sub_requirements": []
        },
        {
          "id": "15741",
          "label": "3",
          "content": [
            {
              "type": "text",
              "value": "Scent item"
            }
          ],
          "resources": [],
          "sub_requirements": []
        },
        {
          "id": "15742",
          "label": "4",
          "content": [
            {
              "type": "text",
              "value": "Area air scent dog"
            }
          ],
          "resources": [],
          "sub_requirements": []
        },
        {
          "id": "15743",
          "label": "5",
          "content": [
            {
              "type": "text",
              "value": "Briefing and debriefing"
            }
          ],
          "resources": [],
          "sub_requirements": []
        },
        {
          "id": "15744",
          "label": "6",
          "content": [
            {
              "type": "text",
              "value": "Clue awareness"
            }
          ],
          "resources": [],
          "sub_requirements": []
        },
        {
          "id": "15745",
          "label": "7",
          "content": [
            {
              "type": "text",
              "value": "Evidence preservation"
            }
          ],
          "resources": [],
          "sub_requirements": []
        },
        {
          "id": "15746",
          "label": "8",
          "content": [
            {
              "type": "text",
              "value": "Tracking a subject"
            }
          ],
          "resources": [],
          "sub_requirements": []
        },
        {
          "id": "15747",
          "label": "9",
          "content": [
            {
              "type": "text",
              "value": "Locating a subject using attraction"
            }
          ],
          "resources": [],
          "sub_requirements": []
        },
        {
          "id": "15748",
          "label": "10",
          "content": [
            {
              "type": "text",
              "value": "Hasty search"
            }
          ],
          "resources": [],
          "sub_requirements": []
        },
        {
          "id": "15749",
          "label": "11",
          "content": [
            {
              "type": "text",
              "value": "Trail sweep search"
            }
          ],
          "resources": [],
          "sub_requirements": []
        },
        {
          "id": "15750",
          "label": "12",
          "content": [
            {
              "type": "text",
              "value": "Grid search."
            }
          ],
          "resources": [],
          "sub_requirements": []
        }
      ]
    },
    {
      "id": "15699",
      "label": "7",
      "content": [
        {
          "type": "element",
          "tag": "b",
          "attrs": {},
          "children": [
            {
              "type": "text",
              "value": "Plan and Complete a Search."
            }
          ]
        },
        {
          "type": "text",
          "value": " Do the following with a team of Scouts, friends, or family to execute a practice SAR exercise:"
        }
      ],
      "resources": [],
      "sub_requirements": [
        {
          "id": "15700",
          "label": "a",
          "content": [
            {
              "type": "text",
              "value": "Choose a hypothetical SAR scenario, either one presented in the "
            },
            {
              "type": "element",
              "tag": "i",
              "attrs": {},
              "children": [
                {
                  "type": "text",
                  "value": "Search and Rescue"
                }
              ]
            },
            {
              "type": "text",
              "value": " merit badge pamphlet or one approved by your counselor."
            }
          ],
          "resources": [],
          "sub_requirements": []
        },
        {
          "id": "15701",
          "label": "b",
          "content": [
            {
              "type": "text",
              "value": "Develop an Incident Action Plan (IAP) for a hasty search using the scenario information."
            }
          ],
          "resources": [],
          "sub_requirements": []
        },
        {
          "id": "15702",
          "label": "c",
          "content": [
            {
              "type": "text",
              "value": "Before the search begins, conduct a PAUSE briefing to review hazards, safety concerns, personal and shared Scout Essentials, and other gear."
            }
          ],
          "resources": [],
          "sub_requirements": []
        },
        {
          "id": "15703",
          "label": "d",
          "content": [
            {
              "type": "text",
              "value": "Execute the search."
            }
          ],
          "resources": [],
          "sub_requirements": []
        },
        {
          "id": "15751",
          "label": "e",
          "content": [
            {
              "type": "text",
              "value": "After the search, hold a team debriefing to discuss the search, problems, successful and unsuccessful tactics, and ideas for improvement."
            }
          ],
          "resources": [],
          "sub_requirements": []
        }
      ]
    },
    {
      "id": "15704",
      "label": "8",
      "content": [
        {
          "type": "element",
          "tag": "b",
          "attrs": {},
          "children": [
            {
              "type": "text",
              "value": "Careers."
            }
          ]
        },
        {
          "type": "text",
          "value": " Do ONE of the following:"
        }
      ],
      "resources": [],
      "sub_requirements": [
        {
          "id": "15705",
          "label": "a",
          "content": [
            {
              "type": "text",
              "value": "Explore careers related to Search and Rescue merit badge or emergency management. Research one career to learn about the training and education needed, costs, job prospects, salary, job duties, and career advancement. With permission of your parent or guardian, your research methods may include an internet or library search, an interview with a professional in the field, or a visit to a location where people in this career work. Discuss with your counselor both your findings and what about this profession might make it an interesting career."
            }
          ],
          "resources": [],
          "sub_requirements": []
        },
        {
          "id": "15706",
          "label": "b",
          "content": [
            {
              "type": "text",
              "value": "Explore how you could use knowledge and skills from this merit badge to serve as a volunteer on a disaster relief team, a wilderness rescue team, or a ski patrol. Research any training needed, expenses, and organizations that promote or support it. Discuss with your counselor what short-term and long-term goals you might have if you pursue this."
            }
          ],
          "resources": [],
          "sub_requirements": []
        }
      ]
    }
  ]
}